[
  {
    "data": [
      {
        "text": "tell me the danger",
        "userDefined": false,
        "id": "8a3536b8-6f3c-5c2d-8aa4-ed11141c230a"
      }
    ],
    "isTemplate": false,
    "count": 0,
    "updated": 0
  },
  {
    "data": [
      {
        "text": "tell me the danger for ",
        "userDefined": false,
        "id": "949f1cf3-df52-519f-b224-b490008223f4"
      },
      {
        "meta": "@list-of-areas",
        "alias": "area",
        "text": "{area}",
        "userDefined": true,
        "id": "a85e7903-ecaa-58c4-afee-b863d08a42a7"
      }
    ],
    "isTemplate": false,
    "count": 0,
    "updated": 0
  },
  {
    "data": [
      {
        "text": "tell me the danger for ",
        "userDefined": false,
        "id": "949f1cf3-df52-519f-b224-b490008223f4"
      },
      {
        "meta": "@list-of-areas",
        "alias": "area",
        "text": "{area}",
        "userDefined": true,
        "id": "a85e7903-ecaa-58c4-afee-b863d08a42a7"
      },
      {
        "text": " ",
        "userDefined": false,
        "id": "41a07dab-dad3-561b-ad06-14cbcd983f62"
      },
      {
        "meta": "@sys.date",
        "alias": "date",
        "text": "{date}",
        "userDefined": true,
        "id": "e6de13c2-af52-5f84-9202-7fc1b73e4532"
      }
    ],
    "isTemplate": false,
    "count": 0,
    "updated": 0
  },
  {
    "data": [
      {
        "text": "tell me the danger for ",
        "userDefined": false,
        "id": "949f1cf3-df52-519f-b224-b490008223f4"
      },
      {
        "meta": "@sys.zip-code",
        "alias": "postcode",
        "text": "{postcode}",
        "userDefined": true,
        "id": "c59c094e-e572-5e47-928d-b998e4bece8f"
      }
    ],
    "isTemplate": false,
    "count": 0,
    "updated": 0
  },
  {
    "data": [
      {
        "text": "tell me the danger for ",
        "userDefined": false,
        "id": "949f1cf3-df52-519f-b224-b490008223f4"
      },
      {
        "meta": "@sys.zip-code",
        "alias": "postcode",
        "text": "{postcode}",
        "userDefined": true,
        "id": "c59c094e-e572-5e47-928d-b998e4bece8f"
      },
      {
        "text": " ",
        "userDefined": false,
        "id": "41a07dab-dad3-561b-ad06-14cbcd983f62"
      },
      {
        "meta": "@sys.date",
        "alias": "date",
        "text": "{date}",
        "userDefined": true,
        "id": "e6de13c2-af52-5f84-9202-7fc1b73e4532"
      }
    ],
    "isTemplate": false,
    "count": 0,
    "updated": 0
  },
  {
    "data": [
      {
        "text": "tell me the danger ",
        "userDefined": false,
        "id": "18c8df26-13eb-5ac9-8e47-474caa8ab888"
      },
      {
        "meta": "@sys.date",
        "alias": "date",
        "text": "{date}",
        "userDefined": true,
        "id": "e6de13c2-af52-5f84-9202-7fc1b73e4532"
      }
    ],
    "isTemplate": false,
    "count": 0,
    "updated": 0
  },
  {
    "data": [
      {
        "text": "tell me the fire danger",
        "userDefined": false,
        "id": "27d6afc0-fc35-59d0-9d93-633a8ff1c16b"
      }
    ],
    "isTemplate": false,
    "count": 0,
    "updated": 0
  },
  {
    "data": [
      {
        "text": "tell me the fire danger for ",
        "userDefined": false,
        "id": "9f891946-4171-52eb-ad26-30043a7e0042"
      },
      {
        "meta": "@list-of-areas",
        "alias": "area",
        "text": "{area}",
        "userDefined": true,
        "id": "a85e7903-ecaa-58c4-afee-b863d08a42a7"
      }
    ],
    "isTemplate": false,
    "count": 0,
    "updated": 0
  },
  {
    "data": [
      {
        "text": "tell me the fire danger for ",
        "userDefined": false,
        "id": "9f891946-4171-52eb-ad26-30043a7e0042"
      },
      {
        "meta": "@list-of-areas",
        "alias": "area",
        "text": "{area}",
        "userDefined": true,
        "id": "a85e7903-ecaa-58c4-afee-b863d08a42a7"
      },
      {
        "text": " ",
        "userDefined": false,
        "id": "41a07dab-dad3-561b-ad06-14cbcd983f62"
      },
      {
        "meta": "@sys.date",
        "alias": "date",
        "text": "{date}",
        "userDefined": true,
        "id": "e6de13c2-af52-5f84-9202-7fc1b73e4532"
      }
    ],
    "isTemplate": false,
    "count": 0,
    "updated": 0
  },
  {
    "data": [
      {
        "text": "tell me the fire danger for ",
        "userDefined": false,
        "id": "9f891946-4171-52eb-ad26-30043a7e0042"
      },
      {
        "meta": "@sys.zip-code",
        "alias": "postcode",
        "text": "{postcode}",
        "userDefined": true,
        "id": "c59c094e-e572-5e47-928d-b998e4bece8f"
      }
    ],
    "isTemplate": false,
    "count": 0,
    "updated": 0
  },
  {
    "data": [
      {
        "text": "tell me the fire danger for ",
        "userDefined": false,
        "id": "9f891946-4171-52eb-ad26-30043a7e0042"
      },
      {
        "meta": "@sys.zip-code",
        "alias": "postcode",
        "text": "{postcode}",
        "userDefined": true,
        "id": "c59c094e-e572-5e47-928d-b998e4bece8f"
      },
      {
        "text": " ",
        "userDefined": false,
        "id": "41a07dab-dad3-561b-ad06-14cbcd983f62"
      },
      {
        "meta": "@sys.date",
        "alias": "date",
        "text": "{date}",
        "userDefined": true,
        "id": "e6de13c2-af52-5f84-9202-7fc1b73e4532"
      }
    ],
    "isTemplate": false,
    "count": 0,
    "updated": 0
  },
  {
    "data": [
      {
        "text": "tell me the fire danger ",
        "userDefined": false,
        "id": "6f6cc898-cf8b-5975-a58b-e55124523187"
      },
      {
        "meta": "@sys.date",
        "alias": "date",
        "text": "{date}",
        "userDefined": true,
        "id": "e6de13c2-af52-5f84-9202-7fc1b73e4532"
      }
    ],
    "isTemplate": false,
    "count": 0,
    "updated": 0
  },
  {
    "data": [
      {
        "text": "tell me the fire level",
        "userDefined": false,
        "id": "d7e5daba-02e9-53da-a2e7-5b71cb4823dd"
      }
    ],
    "isTemplate": false,
    "count": 0,
    "updated": 0
  },
  {
    "data": [
      {
        "text": "tell me the fire level for ",
        "userDefined": false,
        "id": "f06a73a1-80a7-57a0-8f51-af3aa2a10042"
      },
      {
        "meta": "@list-of-areas",
        "alias": "area",
        "text": "{area}",
        "userDefined": true,
        "id": "a85e7903-ecaa-58c4-afee-b863d08a42a7"
      }
    ],
    "isTemplate": false,
    "count": 0,
    "updated": 0
  },
  {
    "data": [
      {
        "text": "tell me the fire level for ",
        "userDefined": false,
        "id": "f06a73a1-80a7-57a0-8f51-af3aa2a10042"
      },
      {
        "meta": "@list-of-areas",
        "alias": "area",
        "text": "{area}",
        "userDefined": true,
        "id": "a85e7903-ecaa-58c4-afee-b863d08a42a7"
      },
      {
        "text": " ",
        "userDefined": false,
        "id": "41a07dab-dad3-561b-ad06-14cbcd983f62"
      },
      {
        "meta": "@sys.date",
        "alias": "date",
        "text": "{date}",
        "userDefined": true,
        "id": "e6de13c2-af52-5f84-9202-7fc1b73e4532"
      }
    ],
    "isTemplate": false,
    "count": 0,
    "updated": 0
  },
  {
    "data": [
      {
        "text": "tell me the fire level for ",
        "userDefined": false,
        "id": "f06a73a1-80a7-57a0-8f51-af3aa2a10042"
      },
      {
        "meta": "@sys.zip-code",
        "alias": "postcode",
        "text": "{postcode}",
        "userDefined": true,
        "id": "c59c094e-e572-5e47-928d-b998e4bece8f"
      }
    ],
    "isTemplate": false,
    "count": 0,
    "updated": 0
  },
  {
    "data": [
      {
        "text": "tell me the fire level for ",
        "userDefined": false,
        "id": "f06a73a1-80a7-57a0-8f51-af3aa2a10042"
      },
      {
        "meta": "@sys.zip-code",
        "alias": "postcode",
        "text": "{postcode}",
        "userDefined": true,
        "id": "c59c094e-e572-5e47-928d-b998e4bece8f"
      },
      {
        "text": " ",
        "userDefined": false,
        "id": "41a07dab-dad3-561b-ad06-14cbcd983f62"
      },
      {
        "meta": "@sys.date",
        "alias": "date",
        "text": "{date}",
        "userDefined": true,
        "id": "e6de13c2-af52-5f84-9202-7fc1b73e4532"
      }
    ],
    "isTemplate": false,
    "count": 0,
    "updated": 0
  },
  {
    "data": [
      {
        "text": "tell me the fire level ",
        "userDefined": false,
        "id": "5abfeb40-63c4-5e12-91d1-c0697f46fb5f"
      },
      {
        "meta": "@sys.date",
        "alias": "date",
        "text": "{date}",
        "userDefined": true,
        "id": "e6de13c2-af52-5f84-9202-7fc1b73e4532"
      }
    ],
    "isTemplate": false,
    "count": 0,
    "updated": 0
  },
  {
    "data": [
      {
        "text": "tell me the fire rating",
        "userDefined": false,
        "id": "f083be99-a712-5c83-baa2-f90bf9b27061"
      }
    ],
    "isTemplate": false,
    "count": 0,
    "updated": 0
  },
  {
    "data": [
      {
        "text": "tell me the fire rating for ",
        "userDefined": false,
        "id": "ea7a0bed-d839-507f-a03f-ad4702c62597"
      },
      {
        "meta": "@list-of-areas",
        "alias": "area",
        "text": "{area}",
        "userDefined": true,
        "id": "a85e7903-ecaa-58c4-afee-b863d08a42a7"
      }
    ],
    "isTemplate": false,
    "count": 0,
    "updated": 0
  },
  {
    "data": [
      {
        "text": "tell me the fire rating for ",
        "userDefined": false,
        "id": "ea7a0bed-d839-507f-a03f-ad4702c62597"
      },
      {
        "meta": "@list-of-areas",
        "alias": "area",
        "text": "{area}",
        "userDefined": true,
        "id": "a85e7903-ecaa-58c4-afee-b863d08a42a7"
      },
      {
        "text": " ",
        "userDefined": false,
        "id": "41a07dab-dad3-561b-ad06-14cbcd983f62"
      },
      {
        "meta": "@sys.date",
        "alias": "date",
        "text": "{date}",
        "userDefined": true,
        "id": "e6de13c2-af52-5f84-9202-7fc1b73e4532"
      }
    ],
    "isTemplate": false,
    "count": 0,
    "updated": 0
  },
  {
    "data": [
      {
        "text": "tell me the fire rating for ",
        "userDefined": false,
        "id": "ea7a0bed-d839-507f-a03f-ad4702c62597"
      },
      {
        "meta": "@sys.zip-code",
        "alias": "postcode",
        "text": "{postcode}",
        "userDefined": true,
        "id": "c59c094e-e572-5e47-928d-b998e4bece8f"
      }
    ],
    "isTemplate": false,
    "count": 0,
    "updated": 0
  },
  {
    "data": [
      {
        "text": "tell me the fire rating for ",
        "userDefined": false,
        "id": "ea7a0bed-d839-507f-a03f-ad4702c62597"
      },
      {
        "meta": "@sys.zip-code",
        "alias": "postcode",
        "text": "{postcode}",
        "userDefined": true,
        "id": "c59c094e-e572-5e47-928d-b998e4bece8f"
      },
      {
        "text": " ",
        "userDefined": false,
        "id": "41a07dab-dad3-561b-ad06-14cbcd983f62"
      },
      {
        "meta": "@sys.date",
        "alias": "date",
        "text": "{date}",
        "userDefined": true,
        "id": "e6de13c2-af52-5f84-9202-7fc1b73e4532"
      }
    ],
    "isTemplate": false,
    "count": 0,
    "updated": 0
  },
  {
    "data": [
      {
        "text": "tell me the fire rating ",
        "userDefined": false,
        "id": "4eb96b3b-c01a-516f-b5d9-1c3ebd2fb336"
      },
      {
        "meta": "@sys.date",
        "alias": "date",
        "text": "{date}",
        "userDefined": true,
        "id": "e6de13c2-af52-5f84-9202-7fc1b73e4532"
      }
    ],
    "isTemplate": false,
    "count": 0,
    "updated": 0
  },
  {
    "data": [
      {
        "text": "tell me the fire safety rating",
        "userDefined": false,
        "id": "5cc50251-3fe0-5fff-ad00-9f161c0209ce"
      }
    ],
    "isTemplate": false,
    "count": 0,
    "updated": 0
  },
  {
    "data": [
      {
        "text": "tell me the fire safety rating for ",
        "userDefined": false,
        "id": "355afd9c-5692-56a1-afd9-90f2c9fc1105"
      },
      {
        "meta": "@list-of-areas",
        "alias": "area",
        "text": "{area}",
        "userDefined": true,
        "id": "a85e7903-ecaa-58c4-afee-b863d08a42a7"
      }
    ],
    "isTemplate": false,
    "count": 0,
    "updated": 0
  },
  {
    "data": [
      {
        "text": "tell me the fire safety rating for ",
        "userDefined": false,
        "id": "355afd9c-5692-56a1-afd9-90f2c9fc1105"
      },
      {
        "meta": "@list-of-areas",
        "alias": "area",
        "text": "{area}",
        "userDefined": true,
        "id": "a85e7903-ecaa-58c4-afee-b863d08a42a7"
      },
      {
        "text": " ",
        "userDefined": false,
        "id": "41a07dab-dad3-561b-ad06-14cbcd983f62"
      },
      {
        "meta": "@sys.date",
        "alias": "date",
        "text": "{date}",
        "userDefined": true,
        "id": "e6de13c2-af52-5f84-9202-7fc1b73e4532"
      }
    ],
    "isTemplate": false,
    "count": 0,
    "updated": 0
  },
  {
    "data": [
      {
        "text": "tell me the fire safety rating for ",
        "userDefined": false,
        "id": "355afd9c-5692-56a1-afd9-90f2c9fc1105"
      },
      {
        "meta": "@sys.zip-code",
        "alias": "postcode",
        "text": "{postcode}",
        "userDefined": true,
        "id": "c59c094e-e572-5e47-928d-b998e4bece8f"
      }
    ],
    "isTemplate": false,
    "count": 0,
    "updated": 0
  },
  {
    "data": [
      {
        "text": "tell me the fire safety rating for ",
        "userDefined": false,
        "id": "355afd9c-5692-56a1-afd9-90f2c9fc1105"
      },
      {
        "meta": "@sys.zip-code",
        "alias": "postcode",
        "text": "{postcode}",
        "userDefined": true,
        "id": "c59c094e-e572-5e47-928d-b998e4bece8f"
      },
      {
        "text": " ",
        "userDefined": false,
        "id": "41a07dab-dad3-561b-ad06-14cbcd983f62"
      },
      {
        "meta": "@sys.date",
        "alias": "date",
        "text": "{date}",
        "userDefined": true,
        "id": "e6de13c2-af52-5f84-9202-7fc1b73e4532"
      }
    ],
    "isTemplate": false,
    "count": 0,
    "updated": 0
  },
  {
    "data": [
      {
        "text": "tell me the fire safety rating ",
        "userDefined": false,
        "id": "8ac2eb6e-c208-5175-8c46-1eb237906bb1"
      },
      {
        "meta": "@sys.date",
        "alias": "date",
        "text": "{date}",
        "userDefined": true,
        "id": "e6de13c2-af52-5f84-9202-7fc1b73e4532"
      }
    ],
    "isTemplate": false,
    "count": 0,
    "updated": 0
  },
  {
    "data": [
      {
        "text": "tell me the fire status",
        "userDefined": false,
        "id": "d6e0db05-4c57-51f4-b781-6b74c73a184e"
      }
    ],
    "isTemplate": false,
    "count": 0,
    "updated": 0
  },
  {
    "data": [
      {
        "text": "tell me the fire status for ",
        "userDefined": false,
        "id": "922ea601-50ba-5740-9b5f-edc7a957da2e"
      },
      {
        "meta": "@list-of-areas",
        "alias": "area",
        "text": "{area}",
        "userDefined": true,
        "id": "a85e7903-ecaa-58c4-afee-b863d08a42a7"
      }
    ],
    "isTemplate": false,
    "count": 0,
    "updated": 0
  },
  {
    "data": [
      {
        "text": "tell me the fire status for ",
        "userDefined": false,
        "id": "922ea601-50ba-5740-9b5f-edc7a957da2e"
      },
      {
        "meta": "@list-of-areas",
        "alias": "area",
        "text": "{area}",
        "userDefined": true,
        "id": "a85e7903-ecaa-58c4-afee-b863d08a42a7"
      },
      {
        "text": " ",
        "userDefined": false,
        "id": "41a07dab-dad3-561b-ad06-14cbcd983f62"
      },
      {
        "meta": "@sys.date",
        "alias": "date",
        "text": "{date}",
        "userDefined": true,
        "id": "e6de13c2-af52-5f84-9202-7fc1b73e4532"
      }
    ],
    "isTemplate": false,
    "count": 0,
    "updated": 0
  },
  {
    "data": [
      {
        "text": "tell me the fire status for ",
        "userDefined": false,
        "id": "922ea601-50ba-5740-9b5f-edc7a957da2e"
      },
      {
        "meta": "@sys.zip-code",
        "alias": "postcode",
        "text": "{postcode}",
        "userDefined": true,
        "id": "c59c094e-e572-5e47-928d-b998e4bece8f"
      }
    ],
    "isTemplate": false,
    "count": 0,
    "updated": 0
  },
  {
    "data": [
      {
        "text": "tell me the fire status for ",
        "userDefined": false,
        "id": "922ea601-50ba-5740-9b5f-edc7a957da2e"
      },
      {
        "meta": "@sys.zip-code",
        "alias": "postcode",
        "text": "{postcode}",
        "userDefined": true,
        "id": "c59c094e-e572-5e47-928d-b998e4bece8f"
      },
      {
        "text": " ",
        "userDefined": false,
        "id": "41a07dab-dad3-561b-ad06-14cbcd983f62"
      },
      {
        "meta": "@sys.date",
        "alias": "date",
        "text": "{date}",
        "userDefined": true,
        "id": "e6de13c2-af52-5f84-9202-7fc1b73e4532"
      }
    ],
    "isTemplate": false,
    "count": 0,
    "updated": 0
  },
  {
    "data": [
      {
        "text": "tell me the fire status ",
        "userDefined": false,
        "id": "3adb8be9-cde8-5cf3-a7a5-05c0221a62e6"
      },
      {
        "meta": "@sys.date",
        "alias": "date",
        "text": "{date}",
        "userDefined": true,
        "id": "e6de13c2-af52-5f84-9202-7fc1b73e4532"
      }
    ],
    "isTemplate": false,
    "count": 0,
    "updated": 0
  },
  {
    "data": [
      {
        "text": "tell me the rating",
        "userDefined": false,
        "id": "3622866a-0845-5e6c-9104-0ab1bde2d130"
      }
    ],
    "isTemplate": false,
    "count": 0,
    "updated": 0
  },
  {
    "data": [
      {
        "text": "tell me the rating for ",
        "userDefined": false,
        "id": "7d229828-f642-5621-a0a3-e0afd8aa402e"
      },
      {
        "meta": "@list-of-areas",
        "alias": "area",
        "text": "{area}",
        "userDefined": true,
        "id": "a85e7903-ecaa-58c4-afee-b863d08a42a7"
      }
    ],
    "isTemplate": false,
    "count": 0,
    "updated": 0
  },
  {
    "data": [
      {
        "text": "tell me the rating for ",
        "userDefined": false,
        "id": "7d229828-f642-5621-a0a3-e0afd8aa402e"
      },
      {
        "meta": "@list-of-areas",
        "alias": "area",
        "text": "{area}",
        "userDefined": true,
        "id": "a85e7903-ecaa-58c4-afee-b863d08a42a7"
      },
      {
        "text": " ",
        "userDefined": false,
        "id": "41a07dab-dad3-561b-ad06-14cbcd983f62"
      },
      {
        "meta": "@sys.date",
        "alias": "date",
        "text": "{date}",
        "userDefined": true,
        "id": "e6de13c2-af52-5f84-9202-7fc1b73e4532"
      }
    ],
    "isTemplate": false,
    "count": 0,
    "updated": 0
  },
  {
    "data": [
      {
        "text": "tell me the rating for ",
        "userDefined": false,
        "id": "7d229828-f642-5621-a0a3-e0afd8aa402e"
      },
      {
        "meta": "@sys.zip-code",
        "alias": "postcode",
        "text": "{postcode}",
        "userDefined": true,
        "id": "c59c094e-e572-5e47-928d-b998e4bece8f"
      }
    ],
    "isTemplate": false,
    "count": 0,
    "updated": 0
  },
  {
    "data": [
      {
        "text": "tell me the rating for ",
        "userDefined": false,
        "id": "7d229828-f642-5621-a0a3-e0afd8aa402e"
      },
      {
        "meta": "@sys.zip-code",
        "alias": "postcode",
        "text": "{postcode}",
        "userDefined": true,
        "id": "c59c094e-e572-5e47-928d-b998e4bece8f"
      },
      {
        "text": " ",
        "userDefined": false,
        "id": "41a07dab-dad3-561b-ad06-14cbcd983f62"
      },
      {
        "meta": "@sys.date",
        "alias": "date",
        "text": "{date}",
        "userDefined": true,
        "id": "e6de13c2-af52-5f84-9202-7fc1b73e4532"
      }
    ],
    "isTemplate": false,
    "count": 0,
    "updated": 0
  },
  {
    "data": [
      {
        "text": "tell me the rating ",
        "userDefined": false,
        "id": "280847c3-3cb2-583d-b304-bb9bd156b411"
      },
      {
        "meta": "@sys.date",
        "alias": "date",
        "text": "{date}",
        "userDefined": true,
        "id": "e6de13c2-af52-5f84-9202-7fc1b73e4532"
      }
    ],
    "isTemplate": false,
    "count": 0,
    "updated": 0
  },
  {
    "data": [
      {
        "text": "what is the danger",
        "userDefined": false,
        "id": "2359483b-0473-5c42-99c6-0346059e49db"
      }
    ],
    "isTemplate": false,
    "count": 0,
    "updated": 0
  },
  {
    "data": [
      {
        "text": "what is the danger for ",
        "userDefined": false,
        "id": "fbe60924-8501-5324-ad61-3068666750f5"
      },
      {
        "meta": "@list-of-areas",
        "alias": "area",
        "text": "{area}",
        "userDefined": true,
        "id": "a85e7903-ecaa-58c4-afee-b863d08a42a7"
      }
    ],
    "isTemplate": false,
    "count": 0,
    "updated": 0
  },
  {
    "data": [
      {
        "text": "what is the danger for ",
        "userDefined": false,
        "id": "fbe60924-8501-5324-ad61-3068666750f5"
      },
      {
        "meta": "@list-of-areas",
        "alias": "area",
        "text": "{area}",
        "userDefined": true,
        "id": "a85e7903-ecaa-58c4-afee-b863d08a42a7"
      },
      {
        "text": " ",
        "userDefined": false,
        "id": "41a07dab-dad3-561b-ad06-14cbcd983f62"
      },
      {
        "meta": "@sys.date",
        "alias": "date",
        "text": "{date}",
        "userDefined": true,
        "id": "e6de13c2-af52-5f84-9202-7fc1b73e4532"
      }
    ],
    "isTemplate": false,
    "count": 0,
    "updated": 0
  },
  {
    "data": [
      {
        "text": "what is the danger for ",
        "userDefined": false,
        "id": "fbe60924-8501-5324-ad61-3068666750f5"
      },
      {
        "meta": "@sys.zip-code",
        "alias": "postcode",
        "text": "{postcode}",
        "userDefined": true,
        "id": "c59c094e-e572-5e47-928d-b998e4bece8f"
      }
    ],
    "isTemplate": false,
    "count": 0,
    "updated": 0
  },
  {
    "data": [
      {
        "text": "what is the danger for ",
        "userDefined": false,
        "id": "fbe60924-8501-5324-ad61-3068666750f5"
      },
      {
        "meta": "@sys.zip-code",
        "alias": "postcode",
        "text": "{postcode}",
        "userDefined": true,
        "id": "c59c094e-e572-5e47-928d-b998e4bece8f"
      },
      {
        "text": " ",
        "userDefined": false,
        "id": "41a07dab-dad3-561b-ad06-14cbcd983f62"
      },
      {
        "meta": "@sys.date",
        "alias": "date",
        "text": "{date}",
        "userDefined": true,
        "id": "e6de13c2-af52-5f84-9202-7fc1b73e4532"
      }
    ],
    "isTemplate": false,
    "count": 0,
    "updated": 0
  },
  {
    "data": [
      {
        "text": "what is the danger ",
        "userDefined": false,
        "id": "2d4bdcc2-4b07-5ab0-8aec-764382f30cd1"
      },
      {
        "meta": "@sys.date",
        "alias": "date",
        "text": "{date}",
        "userDefined": true,
        "id": "e6de13c2-af52-5f84-9202-7fc1b73e4532"
      }
    ],
    "isTemplate": false,
    "count": 0,
    "updated": 0
  },
  {
    "data": [
      {
        "text": "what is the fire danger",
        "userDefined": false,
        "id": "ee6c9ce9-12f4-5231-b6c5-72e07a6125ba"
      }
    ],
    "isTemplate": false,
    "count": 0,
    "updated": 0
  },
  {
    "data": [
      {
        "text": "what is the fire danger for ",
        "userDefined": false,
        "id": "c7af37a1-80e6-522f-9729-8be6553ff85f"
      },
      {
        "meta": "@list-of-areas",
        "alias": "area",
        "text": "{area}",
        "userDefined": true,
        "id": "a85e7903-ecaa-58c4-afee-b863d08a42a7"
      }
    ],
    "isTemplate": false,
    "count": 0,
    "updated": 0
  },
  {
    "data": [
      {
        "text": "what is the fire status for ",
        "userDefined": false,
        "id": "c130752f-ea5a-5931-a49e-b3be499c5ce8"
      },
      {
        "meta": "@sys.zip-code",
        "alias": "postcode",
        "text": "{postcode}",
        "userDefined": true,
        "id": "c59c094e-e572-5e47-928d-b998e4bece8f"
      }
    ],
    "isTemplate": false,
    "count": 0,
    "updated": 0
  },
  {
    "data": [
      {
        "text": "what is the fire status for ",
        "userDefined": false,
        "id": "c130752f-ea5a-5931-a49e-b3be499c5ce8"
      },
      {
        "meta": "@sys.zip-code",
        "alias": "postcode",
        "text": "{postcode}",
        "userDefined": true,
        "id": "c59c094e-e572-5e47-928d-b998e4bece8f"
      },
      {
        "text": " ",
        "userDefined": false,
        "id": "41a07dab-dad3-561b-ad06-14cbcd983f62"
      },
      {
        "meta": "@sys.date",
        "alias": "date",
        "text": "{date}",
        "userDefined": true,
        "id": "e6de13c2-af52-5f84-9202-7fc1b73e4532"
      }
    ],
    "isTemplate": false,
    "count": 0,
    "updated": 0
  },
  {
    "data": [
      {
        "text": "what is the fire status ",
        "userDefined": false,
        "id": "72580324-66a2-5571-9b34-9779bb1942ed"
      },
      {
        "meta": "@sys.date",
        "alias": "date",
        "text": "{date}",
        "userDefined": true,
        "id": "e6de13c2-af52-5f84-9202-7fc1b73e4532"
      }
    ],
    "isTemplate": false,
    "count": 0,
    "updated": 0
  },
  {
    "data": [
      {
        "text": "what is the rating",
        "userDefined": false,
        "id": "dbfbf37d-aa2b-5d58-93b6-4074613eafbe"
      }
    ],
    "isTemplate": false,
    "count": 0,
    "updated": 0
  },
  {
    "data": [
      {
        "text": "what is the rating for ",
        "userDefined": false,
        "id": "e8052676-1645-59f5-b0d1-c3dc57c17e31"
      },
      {
        "meta": "@list-of-areas",
        "alias": "area",
        "text": "{area}",
        "userDefined": true,
        "id": "a85e7903-ecaa-58c4-afee-b863d08a42a7"
      }
    ],
    "isTemplate": false,
    "count": 0,
    "updated": 0
  },
  {
    "data": [
      {
        "text": "what is the rating for ",
        "userDefined": false,
        "id": "e8052676-1645-59f5-b0d1-c3dc57c17e31"
      },
      {
        "meta": "@list-of-areas",
        "alias": "area",
        "text": "{area}",
        "userDefined": true,
        "id": "a85e7903-ecaa-58c4-afee-b863d08a42a7"
      },
      {
        "text": " ",
        "userDefined": false,
        "id": "41a07dab-dad3-561b-ad06-14cbcd983f62"
      },
      {
        "meta": "@sys.date",
        "alias": "date",
        "text": "{date}",
        "userDefined": true,
        "id": "e6de13c2-af52-5f84-9202-7fc1b73e4532"
      }
    ],
    "isTemplate": false,
    "count": 0,
    "updated": 0
  },
  {
    "data": [
      {
        "text": "what is the rating for ",
        "userDefined": false,
        "id": "e8052676-1645-59f5-b0d1-c3dc57c17e31"
      },
      {
        "meta": "@sys.zip-code",
        "alias": "postcode",
        "text": "{postcode}",
        "userDefined": true,
        "id": "c59c094e-e572-5e47-928d-b998e4bece8f"
      }
    ],
    "isTemplate": false,
    "count": 0,
    "updated": 0
  },
  {
    "data": [
      {
        "text": "what is the rating for ",
        "userDefined": false,
        "id": "e8052676-1645-59f5-b0d1-c3dc57c17e31"
      },
      {
        "meta": "@sys.zip-code",
        "alias": "postcode",
        "text": "{postcode}",
        "userDefined": true,
        "id": "c59c094e-e572-5e47-928d-b998e4bece8f"
      },
      {
        "text": " ",
        "userDefined": false,
        "id": "41a07dab-dad3-561b-ad06-14cbcd983f62"
      },
      {
        "meta": "@sys.date",
        "alias": "date",
        "text": "{date}",
        "userDefined": true,
        "id": "e6de13c2-af52-5f84-9202-7fc1b73e4532"
      }
    ],
    "isTemplate": false,
    "count": 0,
    "updated": 0
  },
  {
    "data": [
      {
        "text": "what is the rating ",
        "userDefined": false,
        "id": "1c6c1f6e-fa69-52e0-9fa9-24f57a57d5b6"
      },
      {
        "meta": "@sys.date",
        "alias": "date",
        "text": "{date}",
        "userDefined": true,
        "id": "e6de13c2-af52-5f84-9202-7fc1b73e4532"
      }
    ],
    "isTemplate": false,
    "count": 0,
    "updated": 0
  },
  {
    "data": [
      {
        "text": "what's the danger",
        "userDefined": false,
        "id": "c9a19354-ffa0-59c0-a324-80aa92576018"
      }
    ],
    "isTemplate": false,
    "count": 0,
    "updated": 0
  },
  {
    "data": [
      {
        "text": "what's the danger for ",
        "userDefined": false,
        "id": "d675ab47-aa86-5267-9f31-02d8766895d9"
      },
      {
        "meta": "@list-of-areas",
        "alias": "area",
        "text": "{area}",
        "userDefined": true,
        "id": "a85e7903-ecaa-58c4-afee-b863d08a42a7"
      }
    ],
    "isTemplate": false,
    "count": 0,
    "updated": 0
  },
  {
    "data": [
      {
        "text": "what's the danger for ",
        "userDefined": false,
        "id": "d675ab47-aa86-5267-9f31-02d8766895d9"
      },
      {
        "meta": "@list-of-areas",
        "alias": "area",
        "text": "{area}",
        "userDefined": true,
        "id": "a85e7903-ecaa-58c4-afee-b863d08a42a7"
      },
      {
        "text": " ",
        "userDefined": false,
        "id": "41a07dab-dad3-561b-ad06-14cbcd983f62"
      },
      {
        "meta": "@sys.date",
        "alias": "date",
        "text": "{date}",
        "userDefined": true,
        "id": "e6de13c2-af52-5f84-9202-7fc1b73e4532"
      }
    ],
    "isTemplate": false,
    "count": 0,
    "updated": 0
  },
  {
    "data": [
      {
        "text": "what's the danger for ",
        "userDefined": false,
        "id": "d675ab47-aa86-5267-9f31-02d8766895d9"
      },
      {
        "meta": "@sys.zip-code",
        "alias": "postcode",
        "text": "{postcode}",
        "userDefined": true,
        "id": "c59c094e-e572-5e47-928d-b998e4bece8f"
      }
    ],
    "isTemplate": false,
    "count": 0,
    "updated": 0
  },
  {
    "data": [
      {
        "text": "what's the danger for ",
        "userDefined": false,
        "id": "d675ab47-aa86-5267-9f31-02d8766895d9"
      },
      {
        "meta": "@sys.zip-code",
        "alias": "postcode",
        "text": "{postcode}",
        "userDefined": true,
        "id": "c59c094e-e572-5e47-928d-b998e4bece8f"
      },
      {
        "text": " ",
        "userDefined": false,
        "id": "41a07dab-dad3-561b-ad06-14cbcd983f62"
      },
      {
        "meta": "@sys.date",
        "alias": "date",
        "text": "{date}",
        "userDefined": true,
        "id": "e6de13c2-af52-5f84-9202-7fc1b73e4532"
      }
    ],
    "isTemplate": false,
    "count": 0,
    "updated": 0
  },
  {
    "data": [
      {
        "text": "what's the danger ",
        "userDefined": false,
        "id": "05cf12de-8901-5586-81a8-9b905e951db0"
      },
      {
        "meta": "@sys.date",
        "alias": "date",
        "text": "{date}",
        "userDefined": true,
        "id": "e6de13c2-af52-5f84-9202-7fc1b73e4532"
      }
    ],
    "isTemplate": false,
    "count": 0,
    "updated": 0
  },
  {
    "data": [
      {
        "text": "what's the fire danger",
        "userDefined": false,
        "id": "e927de28-aa2e-50e6-883d-10ce32c58730"
      }
    ],
    "isTemplate": false,
    "count": 0,
    "updated": 0
  },
  {
    "data": [
      {
        "text": "what's the fire danger for ",
        "userDefined": false,
        "id": "7782e482-8317-58fa-b222-cf2367fbd062"
      },
      {
        "meta": "@list-of-areas",
        "alias": "area",
        "text": "{area}",
        "userDefined": true,
        "id": "a85e7903-ecaa-58c4-afee-b863d08a42a7"
      }
    ],
    "isTemplate": false,
    "count": 0,
    "updated": 0
  },
  {
    "data": [
      {
        "text": "what's the fire danger for ",
        "userDefined": false,
        "id": "7782e482-8317-58fa-b222-cf2367fbd062"
      },
      {
        "meta": "@list-of-areas",
        "alias": "area",
        "text": "{area}",
        "userDefined": true,
        "id": "a85e7903-ecaa-58c4-afee-b863d08a42a7"
      },
      {
        "text": " ",
        "userDefined": false,
        "id": "41a07dab-dad3-561b-ad06-14cbcd983f62"
      },
      {
        "meta": "@sys.date",
        "alias": "date",
        "text": "{date}",
        "userDefined": true,
        "id": "e6de13c2-af52-5f84-9202-7fc1b73e4532"
      }
    ],
    "isTemplate": false,
    "count": 0,
    "updated": 0
  },
  {
    "data": [
      {
        "text": "what's the fire danger for ",
        "userDefined": false,
        "id": "7782e482-8317-58fa-b222-cf2367fbd062"
      },
      {
        "meta": "@sys.zip-code",
        "alias": "postcode",
        "text": "{postcode}",
        "userDefined": true,
        "id": "c59c094e-e572-5e47-928d-b998e4bece8f"
      }
    ],
    "isTemplate": false,
    "count": 0,
    "updated": 0
  },
  {
    "data": [
      {
        "text": "what's the fire danger for ",
        "userDefined": false,
        "id": "7782e482-8317-58fa-b222-cf2367fbd062"
      },
      {
        "meta": "@sys.zip-code",
        "alias": "postcode",
        "text": "{postcode}",
        "userDefined": true,
        "id": "c59c094e-e572-5e47-928d-b998e4bece8f"
      },
      {
        "text": " ",
        "userDefined": false,
        "id": "41a07dab-dad3-561b-ad06-14cbcd983f62"
      },
      {
        "meta": "@sys.date",
        "alias": "date",
        "text": "{date}",
        "userDefined": true,
        "id": "e6de13c2-af52-5f84-9202-7fc1b73e4532"
      }
    ],
    "isTemplate": false,
    "count": 0,
    "updated": 0
  },
  {
    "data": [
      {
        "text": "what's the fire danger ",
        "userDefined": false,
        "id": "7fad6b0a-efa5-5701-befb-1476f98953ab"
      },
      {
        "meta": "@sys.date",
        "alias": "date",
        "text": "{date}",
        "userDefined": true,
        "id": "e6de13c2-af52-5f84-9202-7fc1b73e4532"
      }
    ],
    "isTemplate": false,
    "count": 0,
    "updated": 0
  },
  {
    "data": [
      {
        "text": "what's the fire level",
        "userDefined": false,
        "id": "c7925fdc-0f17-5e60-92d6-b2d8cd5782de"
      }
    ],
    "isTemplate": false,
    "count": 0,
    "updated": 0
  },
  {
    "data": [
      {
        "text": "what's the fire level for ",
        "userDefined": false,
        "id": "bca5c547-4e19-54d1-aa32-6c2c9ebc8045"
      },
      {
        "meta": "@list-of-areas",
        "alias": "area",
        "text": "{area}",
        "userDefined": true,
        "id": "a85e7903-ecaa-58c4-afee-b863d08a42a7"
      }
    ],
    "isTemplate": false,
    "count": 0,
    "updated": 0
  },
  {
    "data": [
      {
        "text": "what's the fire level for ",
        "userDefined": false,
        "id": "bca5c547-4e19-54d1-aa32-6c2c9ebc8045"
      },
      {
        "meta": "@list-of-areas",
        "alias": "area",
        "text": "{area}",
        "userDefined": true,
        "id": "a85e7903-ecaa-58c4-afee-b863d08a42a7"
      },
      {
        "text": " ",
        "userDefined": false,
        "id": "41a07dab-dad3-561b-ad06-14cbcd983f62"
      },
      {
        "meta": "@sys.date",
        "alias": "date",
        "text": "{date}",
        "userDefined": true,
        "id": "e6de13c2-af52-5f84-9202-7fc1b73e4532"
      }
    ],
    "isTemplate": false,
    "count": 0,
    "updated": 0
  },
  {
    "data": [
      {
        "text": "what's the fire level for ",
        "userDefined": false,
        "id": "bca5c547-4e19-54d1-aa32-6c2c9ebc8045"
      },
      {
        "meta": "@sys.zip-code",
        "alias": "postcode",
        "text": "{postcode}",
        "userDefined": true,
        "id": "c59c094e-e572-5e47-928d-b998e4bece8f"
      }
    ],
    "isTemplate": false,
    "count": 0,
    "updated": 0
  },
  {
    "data": [
      {
        "text": "what's the fire level for ",
        "userDefined": false,
        "id": "bca5c547-4e19-54d1-aa32-6c2c9ebc8045"
      },
      {
        "meta": "@sys.zip-code",
        "alias": "postcode",
        "text": "{postcode}",
        "userDefined": true,
        "id": "c59c094e-e572-5e47-928d-b998e4bece8f"
      },
      {
        "text": " ",
        "userDefined": false,
        "id": "41a07dab-dad3-561b-ad06-14cbcd983f62"
      },
      {
        "meta": "@sys.date",
        "alias": "date",
        "text": "{date}",
        "userDefined": true,
        "id": "e6de13c2-af52-5f84-9202-7fc1b73e4532"
      }
    ],
    "isTemplate": false,
    "count": 0,
    "updated": 0
  },
  {
    "data": [
      {
        "text": "what's the fire level ",
        "userDefined": false,
        "id": "607f7ac8-f6bc-54e3-a1b3-fcf70b425ac0"
      },
      {
        "meta": "@sys.date",
        "alias": "date",
        "text": "{date}",
        "userDefined": true,
        "id": "e6de13c2-af52-5f84-9202-7fc1b73e4532"
      }
    ],
    "isTemplate": false,
    "count": 0,
    "updated": 0
  },
  {
    "data": [
      {
        "text": "what's the fire rating",
        "userDefined": false,
        "id": "ed892b06-c841-516d-b09e-175c2b6b03c9"
      }
    ],
    "isTemplate": false,
    "count": 0,
    "updated": 0
  },
  {
    "data": [
      {
        "text": "what's the fire rating for ",
        "userDefined": false,
        "id": "6e4028a2-835b-561a-99c4-56b66642a352"
      },
      {
        "meta": "@list-of-areas",
        "alias": "area",
        "text": "{area}",
        "userDefined": true,
        "id": "a85e7903-ecaa-58c4-afee-b863d08a42a7"
      }
    ],
    "isTemplate": false,
    "count": 0,
    "updated": 0
  },
  {
    "data": [
      {
        "text": "what's the fire rating for ",
        "userDefined": false,
        "id": "6e4028a2-835b-561a-99c4-56b66642a352"
      },
      {
        "meta": "@list-of-areas",
        "alias": "area",
        "text": "{area}",
        "userDefined": true,
        "id": "a85e7903-ecaa-58c4-afee-b863d08a42a7"
      },
      {
        "text": " ",
        "userDefined": false,
        "id": "41a07dab-dad3-561b-ad06-14cbcd983f62"
      },
      {
        "meta": "@sys.date",
        "alias": "date",
        "text": "{date}",
        "userDefined": true,
        "id": "e6de13c2-af52-5f84-9202-7fc1b73e4532"
      }
    ],
    "isTemplate": false,
    "count": 0,
    "updated": 0
  },
  {
    "data": [
      {
        "text": "what's the fire rating for ",
        "userDefined": false,
        "id": "6e4028a2-835b-561a-99c4-56b66642a352"
      },
      {
        "meta": "@sys.zip-code",
        "alias": "postcode",
        "text": "{postcode}",
        "userDefined": true,
        "id": "c59c094e-e572-5e47-928d-b998e4bece8f"
      }
    ],
    "isTemplate": false,
    "count": 0,
    "updated": 0
  },
  {
    "data": [
      {
        "text": "what's the fire rating for ",
        "userDefined": false,
        "id": "6e4028a2-835b-561a-99c4-56b66642a352"
      },
      {
        "meta": "@sys.zip-code",
        "alias": "postcode",
        "text": "{postcode}",
        "userDefined": true,
        "id": "c59c094e-e572-5e47-928d-b998e4bece8f"
      },
      {
        "text": " ",
        "userDefined": false,
        "id": "41a07dab-dad3-561b-ad06-14cbcd983f62"
      },
      {
        "meta": "@sys.date",
        "alias": "date",
        "text": "{date}",
        "userDefined": true,
        "id": "e6de13c2-af52-5f84-9202-7fc1b73e4532"
      }
    ],
    "isTemplate": false,
    "count": 0,
    "updated": 0
  },
  {
    "data": [
      {
        "text": "what's the fire rating ",
        "userDefined": false,
        "id": "43c1391b-caf7-5fa3-9d7d-3cb48b31a123"
      },
      {
        "meta": "@sys.date",
        "alias": "date",
        "text": "{date}",
        "userDefined": true,
        "id": "e6de13c2-af52-5f84-9202-7fc1b73e4532"
      }
    ],
    "isTemplate": false,
    "count": 0,
    "updated": 0
  },
  {
    "data": [
      {
        "text": "what's the fire safety rating",
        "userDefined": false,
        "id": "803a94cc-d23a-5342-976e-2291b45cc7fe"
      }
    ],
    "isTemplate": false,
    "count": 0,
    "updated": 0
  },
  {
    "data": [
      {
        "text": "what's the fire safety rating for ",
        "userDefined": false,
        "id": "00b5147e-5648-5f07-92ba-0be8258e5756"
      },
      {
        "meta": "@list-of-areas",
        "alias": "area",
        "text": "{area}",
        "userDefined": true,
        "id": "a85e7903-ecaa-58c4-afee-b863d08a42a7"
      }
    ],
    "isTemplate": false,
    "count": 0,
    "updated": 0
  },
  {
    "data": [
      {
        "text": "what's the fire safety rating for ",
        "userDefined": false,
        "id": "00b5147e-5648-5f07-92ba-0be8258e5756"
      },
      {
        "meta": "@list-of-areas",
        "alias": "area",
        "text": "{area}",
        "userDefined": true,
        "id": "a85e7903-ecaa-58c4-afee-b863d08a42a7"
      },
      {
        "text": " ",
        "userDefined": false,
        "id": "41a07dab-dad3-561b-ad06-14cbcd983f62"
      },
      {
        "meta": "@sys.date",
        "alias": "date",
        "text": "{date}",
        "userDefined": true,
        "id": "e6de13c2-af52-5f84-9202-7fc1b73e4532"
      }
    ],
    "isTemplate": false,
    "count": 0,
    "updated": 0
  },
  {
    "data": [
      {
        "text": "what's the fire safety rating for ",
        "userDefined": false,
        "id": "00b5147e-5648-5f07-92ba-0be8258e5756"
      },
      {
        "meta": "@sys.zip-code",
        "alias": "postcode",
        "text": "{postcode}",
        "userDefined": true,
        "id": "c59c094e-e572-5e47-928d-b998e4bece8f"
      }
    ],
    "isTemplate": false,
    "count": 0,
    "updated": 0
  },
  {
    "data": [
      {
        "text": "what's the fire safety rating for ",
        "userDefined": false,
        "id": "00b5147e-5648-5f07-92ba-0be8258e5756"
      },
      {
        "meta": "@sys.zip-code",
        "alias": "postcode",
        "text": "{postcode}",
        "userDefined": true,
        "id": "c59c094e-e572-5e47-928d-b998e4bece8f"
      },
      {
        "text": " ",
        "userDefined": false,
        "id": "41a07dab-dad3-561b-ad06-14cbcd983f62"
      },
      {
        "meta": "@sys.date",
        "alias": "date",
        "text": "{date}",
        "userDefined": true,
        "id": "e6de13c2-af52-5f84-9202-7fc1b73e4532"
      }
    ],
    "isTemplate": false,
    "count": 0,
    "updated": 0
  },
  {
    "data": [
      {
        "text": "what's the fire safety rating ",
        "userDefined": false,
        "id": "ed558832-7cb6-5e14-a498-9e9f1e4fead9"
      },
      {
        "meta": "@sys.date",
        "alias": "date",
        "text": "{date}",
        "userDefined": true,
        "id": "e6de13c2-af52-5f84-9202-7fc1b73e4532"
      }
    ],
    "isTemplate": false,
    "count": 0,
    "updated": 0
  },
  {
    "data": [
      {
        "text": "what's the fire status",
        "userDefined": false,
        "id": "ace1cbf2-d966-54d8-ac1c-3c003742a756"
      }
    ],
    "isTemplate": false,
    "count": 0,
    "updated": 0
  },
  {
    "data": [
      {
        "text": "what's the fire status for ",
        "userDefined": false,
        "id": "c56fdb3c-5c33-5d9d-8373-d8b078ecc1eb"
      },
      {
        "meta": "@list-of-areas",
        "alias": "area",
        "text": "{area}",
        "userDefined": true,
        "id": "a85e7903-ecaa-58c4-afee-b863d08a42a7"
      }
    ],
    "isTemplate": false,
    "count": 0,
    "updated": 0
  },
  {
    "data": [
      {
        "text": "what's the fire status for ",
        "userDefined": false,
        "id": "c56fdb3c-5c33-5d9d-8373-d8b078ecc1eb"
      },
      {
        "meta": "@list-of-areas",
        "alias": "area",
        "text": "{area}",
        "userDefined": true,
        "id": "a85e7903-ecaa-58c4-afee-b863d08a42a7"
      },
      {
        "text": " ",
        "userDefined": false,
        "id": "41a07dab-dad3-561b-ad06-14cbcd983f62"
      },
      {
        "meta": "@sys.date",
        "alias": "date",
        "text": "{date}",
        "userDefined": true,
        "id": "e6de13c2-af52-5f84-9202-7fc1b73e4532"
      }
    ],
    "isTemplate": false,
    "count": 0,
    "updated": 0
  },
  {
    "data": [
      {
        "text": "what's the fire status for ",
        "userDefined": false,
        "id": "c56fdb3c-5c33-5d9d-8373-d8b078ecc1eb"
      },
      {
        "meta": "@sys.zip-code",
        "alias": "postcode",
        "text": "{postcode}",
        "userDefined": true,
        "id": "c59c094e-e572-5e47-928d-b998e4bece8f"
      }
    ],
    "isTemplate": false,
    "count": 0,
    "updated": 0
  },
  {
    "data": [
      {
        "text": "what's the fire status for ",
        "userDefined": false,
        "id": "c56fdb3c-5c33-5d9d-8373-d8b078ecc1eb"
      },
      {
        "meta": "@sys.zip-code",
        "alias": "postcode",
        "text": "{postcode}",
        "userDefined": true,
        "id": "c59c094e-e572-5e47-928d-b998e4bece8f"
      },
      {
        "text": " ",
        "userDefined": false,
        "id": "41a07dab-dad3-561b-ad06-14cbcd983f62"
      },
      {
        "meta": "@sys.date",
        "alias": "date",
        "text": "{date}",
        "userDefined": true,
        "id": "e6de13c2-af52-5f84-9202-7fc1b73e4532"
      }
    ],
    "isTemplate": false,
    "count": 0,
    "updated": 0
  },
  {
    "data": [
      {
        "text": "what's the fire status ",
        "userDefined": false,
        "id": "5ed1a2a3-37f2-5775-816f-8cca68d79d82"
      },
      {
        "meta": "@sys.date",
        "alias": "date",
        "text": "{date}",
        "userDefined": true,
        "id": "e6de13c2-af52-5f84-9202-7fc1b73e4532"
      }
    ],
    "isTemplate": false,
    "count": 0,
    "updated": 0
  },
  {
    "data": [
      {
        "text": "what's the rating",
        "userDefined": false,
        "id": "45cdd068-12af-5b45-86e4-baabe24c6a23"
      }
    ],
    "isTemplate": false,
    "count": 0,
    "updated": 0
  },
  {
    "data": [
      {
        "text": "what's the rating for ",
        "userDefined": false,
        "id": "c3b36be5-81ee-5f04-933a-43cc57e98978"
      },
      {
        "meta": "@list-of-areas",
        "alias": "area",
        "text": "{area}",
        "userDefined": true,
        "id": "a85e7903-ecaa-58c4-afee-b863d08a42a7"
      }
    ],
    "isTemplate": false,
    "count": 0,
    "updated": 0
  },
  {
    "data": [
      {
        "text": "what's the rating for ",
        "userDefined": false,
        "id": "c3b36be5-81ee-5f04-933a-43cc57e98978"
      },
      {
        "meta": "@list-of-areas",
        "alias": "area",
        "text": "{area}",
        "userDefined": true,
        "id": "a85e7903-ecaa-58c4-afee-b863d08a42a7"
      },
      {
        "text": " ",
        "userDefined": false,
        "id": "41a07dab-dad3-561b-ad06-14cbcd983f62"
      },
      {
        "meta": "@sys.date",
        "alias": "date",
        "text": "{date}",
        "userDefined": true,
        "id": "e6de13c2-af52-5f84-9202-7fc1b73e4532"
      }
    ],
    "isTemplate": false,
    "count": 0,
    "updated": 0
  },
  {
    "data": [
      {
        "text": "what's the rating for ",
        "userDefined": false,
        "id": "c3b36be5-81ee-5f04-933a-43cc57e98978"
      },
      {
        "meta": "@sys.zip-code",
        "alias": "postcode",
        "text": "{postcode}",
        "userDefined": true,
        "id": "c59c094e-e572-5e47-928d-b998e4bece8f"
      }
    ],
    "isTemplate": false,
    "count": 0,
    "updated": 0
  },
  {
    "data": [
      {
        "text": "what's the rating for ",
        "userDefined": false,
        "id": "c3b36be5-81ee-5f04-933a-43cc57e98978"
      },
      {
        "meta": "@sys.zip-code",
        "alias": "postcode",
        "text": "{postcode}",
        "userDefined": true,
        "id": "c59c094e-e572-5e47-928d-b998e4bece8f"
      },
      {
        "text": " ",
        "userDefined": false,
        "id": "41a07dab-dad3-561b-ad06-14cbcd983f62"
      },
      {
        "meta": "@sys.date",
        "alias": "date",
        "text": "{date}",
        "userDefined": true,
        "id": "e6de13c2-af52-5f84-9202-7fc1b73e4532"
      }
    ],
    "isTemplate": false,
    "count": 0,
    "updated": 0
  },
  {
    "data": [
      {
        "text": "what's the rating ",
        "userDefined": false,
        "id": "099c294d-b231-5550-b61d-3d09b8e9c7f8"
      },
      {
        "meta": "@sys.date",
        "alias": "date",
        "text": "{date}",
        "userDefined": true,
        "id": "e6de13c2-af52-5f84-9202-7fc1b73e4532"
      }
    ],
    "isTemplate": false,
    "count": 0,
    "updated": 0
  },
  {
    "data": [
      {
        "text": "what's the fire danger rating for ",
        "userDefined": false,
        "id": "06d39dfb-40ea-524b-a896-634d2640c93b"
      },
      {
        "meta": "@list-of-areas",
        "alias": "area",
        "text": "{area}",
        "userDefined": true,
        "id": "a85e7903-ecaa-58c4-afee-b863d08a42a7"
      }
    ],
    "isTemplate": false,
    "count": 0,
    "updated": 0
  },
  {
    "data": [
      {
        "text": "what's the fire danger rating for ",
        "userDefined": false,
        "id": "06d39dfb-40ea-524b-a896-634d2640c93b"
      },
      {
        "meta": "@sys.zip-code",
        "alias": "postcode",
        "text": "{postcode}",
        "userDefined": true,
        "id": "c59c094e-e572-5e47-928d-b998e4bece8f"
      }
    ],
    "isTemplate": false,
    "count": 0,
    "updated": 0
  },
  {
    "data": [
      {
        "text": "what's the fire danger rating",
        "userDefined": false,
        "id": "8ea37703-b1c2-501f-80b8-3808a778629f"
      }
    ],
    "isTemplate": false,
    "count": 0,
    "updated": 0
  }
]